amazon_wishlist_pricewatch/__init__.py
amazon_wishlist_pricewatch/config.json
amazon_wishlist_pricewatch/logger.py
amazon_wishlist_pricewatch/my_types.py
amazon_wishlist_pricewatch/notify.py
amazon_wishlist_pricewatch/pricewatch.py
amazon_wishlist_pricewatch/version.py
amazon_wishlist_pricewatch-0.1.24.dist-info/LICENSE.txt
amazon_wishlist_pricewatch-0.1.24.dist-info/METADATA
amazon_wishlist_pricewatch-0.1.24.dist-info/WHEEL
amazon_wishlist_pricewatch-0.1.24.dist-info/entry_points.txt
amazon_wishlist_pricewatch-0.1.24.dist-info/top_level.txt
amazon_wishlist_pricewatch-0.1.24.dist-info/RECORD
