Metadata-Version: 2.1
Name: amazon-wishlist-pricewatch
Version: 0.1.24
Summary: Periodically check your Amazon wishlist for price reductions.
Home-page: https://github.com/sam0jones0/amazon_wishlist_pricewatch
Author: Sam Jones
Author-email: sam0jones0@gmail.com
License: MIT license
Project-URL: Bug Reports, https://github.com/sam0jones0/amazon_wishlist_pricewatch/issues
Project-URL: Say Thanks!, https://github.com/sam0jones0/amazon_wishlist_pricewatch/stargazers
Project-URL: Source, https://github.com/sam0jones0/amazon_wishlist_pricewatch
Keywords: amazon,wishlist,price,checker,price cut,deal
Platform: UNKNOWN
Classifier: Development Status :: 3 - Alpha
Classifier: Environment :: Console
Classifier: Framework :: Pytest
Classifier: Intended Audience :: Developers
Classifier: Intended Audience :: End Users/Desktop
Classifier: License :: OSI Approved :: MIT License
Classifier: Natural Language :: English
Classifier: Operating System :: OS Independent
Classifier: Topic :: Internet :: WWW/HTTP :: Site Management :: Link Checking
Classifier: Topic :: Utilities
Classifier: Typing :: Typed
Classifier: Programming Language :: Python :: 3
Classifier: Programming Language :: Python :: 3.8
Classifier: Programming Language :: Python :: 3.9
Classifier: Programming Language :: Python :: 3 :: Only
Requires-Python: <4,>=3.8
License-File: LICENSE.txt
Requires-Dist: beautifulsoup4
Requires-Dist: requests
Provides-Extra: dev
Requires-Dist: black ; extra == 'dev'
Requires-Dist: mypy ; extra == 'dev'
Provides-Extra: telegram
Requires-Dist: python-telegram-bot ; extra == 'telegram'
Provides-Extra: test
Requires-Dist: pytest ; extra == 'test'
